selfphish/__init__.py
selfphish/_version.py
selfphish/config.json
selfphish/ganrec.py
selfphish/loss.py
selfphish/models.py
selfphish/propagators.py
selfphish/tfutils.py
selfphish/utils.py
selfphish-0.1.1.dist-info/METADATA
selfphish-0.1.1.dist-info/WHEEL
selfphish-0.1.1.dist-info/licenses/AUTHORS.rst
selfphish-0.1.1.dist-info/licenses/LICENSE
selfphish-0.1.1.dist-info/RECORD
