Metadata-Version: 2.4
Name: selfphish
Version: 0.1.1
Summary: A deep neural network data reconstruction platform for phase retreival
Project-URL: homepage, https://github.com/XYangXRay/selfphish
Project-URL: repository, https://github.com/XYangXRay/selfphish
Project-URL: documentation, https://github.com/XYangXRay/selfphish
Author-email: Xiaogang Yang <xiaogang.yang@outlook.com>
License: BSD 3-Clause License
License-File: AUTHORS.rst
License-File: LICENSE
Keywords: Data reconstruction,GAN,Phase retrieval
Classifier: License :: OSI Approved :: MIT License
Classifier: Operating System :: OS Independent
Classifier: Programming Language :: Python :: 3
Requires-Python: >=3.10
Requires-Dist: ipython>=8.36.0
Requires-Dist: matplotlib>=3.7.3
Requires-Dist: numpy>=1.25.0
Requires-Dist: scikit-image>=0.21.1
Requires-Dist: tensorflow[and-cuda]>=2.16.0
Requires-Dist: tifffile>=2024.08.01
Requires-Dist: tqdm>=4.66.1
Provides-Extra: pytorch
Requires-Dist: quantities; extra == 'pytorch'
Requires-Dist: torch>=2.7.0; extra == 'pytorch'
Requires-Dist: torchvision; extra == 'pytorch'
